{
  "gitSyncId": "669ea42eae21844540eb6892_fa2b1222-f425-48f5-833f-aac6f2c563a3",
  "id": "Page1 Copy_JSObject1.myFun1",
  "pluginId": "js-plugin",
  "pluginType": "JS",
  "unpublishedAction": {
    "actionConfiguration": {
      "encodeParamsToggle": true,
      "jsArguments": [],
      "paginationType": "NONE",
      "timeoutInMillisecond": 10000
    },
    "clientSideExecution": true,
    "collectionId": "Page1 Copy_JSObject1",
    "confirmBeforeExecute": false,
    "datasource": {
      "isAutoGenerated": false,
      "name": "UNUSED_DATASOURCE",
      "pluginId": "js-plugin"
    },
    "dynamicBindingPathList": [
      {
        "key": "body"
      }
    ],
    "executeOnLoad": false,
    "fullyQualifiedName": "JSObject1.myFun1",
    "name": "myFun1",
    "pageId": "Page1 Copy",
    "userSetOnLoad": false
  }
}